tsp_2opt-0.0.1.dist-info/METADATA
tsp_2opt-0.0.1.dist-info/WHEEL
tsp_2opt/.DS_Store
tsp_2opt/solver.py
tsp_2opt/__init__.py
tsp_2opt/utils.py
tsp_2opt/main.py
tsp_2opt/tsp_2opt.cpython-38-darwin.so
tsp_2opt-0.0.1.dist-info/RECORD
