Metadata-Version: 2.1
Name: tsp_2opt
Version: 0.0.1
Requires-Dist: numpy>=1.20.1
Home-Page: https://github.com/mehdibnc/TSP2opt
Author: mehdi <mehdi-bs@live.fr>
Author-Email: mehdi <mehdi-bs@live.fr>
Maintainer: Mehdi Bnc
Maintainer-Email: mehdi-bs@live.fr
License: MIT
Requires-Python: >=3.7
